incept/__init__.py
incept/asset_generator.py
incept/cli.py
incept/config.py
incept/courses.py
incept/dbfactory.py
incept/dl_rebelway.py
incept/dl_video.py
incept/notiondb.py
incept/payload.py
incept/poster.py
incept/postgresdb.py
incept/projects.py
incept/templates.py
incept/utils.py
incept/.config/env.example
incept/.config/fonts/coresansc15.otf
incept/.config/fonts/coresansc15it.otf
incept/.config/fonts/coresansc25.otf
incept/.config/fonts/coresansc25it.otf
incept/.config/fonts/coresansc35.otf
incept/.config/fonts/coresansc35it.otf
incept/.config/fonts/coresansc45.otf
incept/.config/fonts/coresansc45it.otf
incept/.config/fonts/coresansc55.otf
incept/.config/fonts/coresansc55it.otf
incept/.config/fonts/coresansc65.otf
incept/.config/fonts/coresansc65it.otf
incept/.config/fonts/coresansc75.otf
incept/.config/fonts/coresansc75it.otf
incept/.config/fonts/coresansc85.otf
incept/.config/fonts/coresansc85it.otf
incept/.config/fonts/coresansc95.otf
incept/.config/fonts/coresansc95it.otf
incept/.config/mapping/notion_mapping.json
incept/.config/payload/chapters.csv
incept/.config/payload/chapters.json
incept/.config/payload/cine_light.json
incept/.config/payload/courses.json
incept/.config/payload/full_courses.json
incept/.config/payload/lessons.csv
incept/.config/payload/lessons.json
incept/.config/payload/notion_lessons.json
incept/.config/templates/default_chapter.j2
incept/.config/templates/default_course.j2
incept/.config/templates/default_lesson.j2
incept/.config/templates/rebelway.j2
incept/.config/templates/templates.json
incept/.config/templates/video_chapter.j2
incept/.config/templates/video_course.j2
incept/.config/templates/video_lesson.j2
incept-0.1.116.dist-info/METADATA
incept-0.1.116.dist-info/WHEEL
incept-0.1.116.dist-info/entry_points.txt
incept-0.1.116.dist-info/licenses/LICENSE
incept-0.1.116.dist-info/RECORD
