Metadata-Version: 2.4
Name: incept
Version: 0.1.116
Summary: A Python package for managing courses, projects, and directories with Notion integration.
Project-URL: Homepage, https://github.com/suhailphotos/Incept
Project-URL: Repository, https://github.com/suhailphotos/Incept
Project-URL: Issues, https://github.com/suhailphotos/Incept/issues
Author-email: Suhail <suhailece@gmail.com>
License: MIT License
License-File: LICENSE
Requires-Python: <4.0,>=3.11
Requires-Dist: beautifulsoup4<5.0.0,>=4.13.4
Requires-Dist: browser-cookie3<0.21.0,>=0.20.1
Requires-Dist: click<9.0.0,>=8.1.8
Requires-Dist: jinja2<4.0.0,>=3.1.5
Requires-Dist: notionmanager<0.2.0,>=0.1.28
Requires-Dist: oauthmanager<0.2.0,>=0.1.1
Requires-Dist: openpyxl<4.0.0,>=3.1.5
Requires-Dist: packaging<24.3
Requires-Dist: pandas<3.0.0,>=2.2.3
Requires-Dist: pillow<12.0.0,>=11.1.0
Requires-Dist: platformdirs<4.0.0,>=3.0.0
Requires-Dist: prefect-github>=0.3.0
Requires-Dist: prefect<4,>=3.2.12
Requires-Dist: python-dotenv<2.0.0,>=1.1.0
Requires-Dist: requests<3.0.0,>=2.32.3
Requires-Dist: selenium<5.0.0,>=4.31.0
Requires-Dist: tabulate<0.10.0,>=0.9.0
Requires-Dist: webdriver-manager<5.0.0,>=4.0.2
